modules/alu.v
// ALU expecífica

// op:
//      00 -> +
//      01 -> -
//      10 -> <<
//      11 -> &

// OPERAR:
//      0: deja pasar in_b
//      1: opera


module alu #(parameter N = 8, N_OP = 2) (
    input [N-1:0] in_a,
    input [N-1:0] in_b,
    input [N_OP-1:0] op,
    input operar,
    output reg [N-1:0] out,
    output reg z, n, v
);

always @(*) begin
    if(operar) begin
        case(op)
            'b00: out = in_a + in_b;
            'b01: out = in_a - in_b;
            // Extiende el signo
            'b10: out = in_a[N-1] ? (in_a >> 1) | 1 << N-1 : (in_a >> 1);
            'b11: out = in_a & in_b;
            default: out = 8'd0;
        endcase
    end
    else
        out = in_b;

    z = out == 0 ? 1 : 0;
end

endmodule

modules/tb/alu_tb.v
`include "../alu.v"
`timescale 1s/1ms

module alu_tb;


localparam N = 16;

reg [N-1:0] alu_in_a, alu_in_b;
reg [1:0] alu_op;
reg alu_operar;

wire [N-1:0] alu_out;
wire alu_z;


alu #(.N(N)) ALU_1 (
    .in_a(alu_in_a),
    .in_b(alu_in_b),
    .op(alu_op),
    .operar(alu_operar),
    .out(alu_out),
    .z(alu_z)
);

initial begin
    $dumpfile("alu_tb.vcd");
    $dumpvars(0, alu_tb);

    alu_operar = 1;
    alu_in_a = 16'd10;
    alu_in_b = 16'd5;

    alu_op = 2'b00; // Sumamos

    # 1
    alu_op = 2'b01;  // Restamos

    # 1
    alu_op = 2'b10;  // Right shift

    # 1
    alu_op = 2'b11;  // And

    # 1
    alu_in_a = -10;
    alu_in_b = 16'd5;

    alu_op = 2'b00; // Sumamos

    # 1
    alu_op = 2'b01;  // Restamos

    # 1
    alu_op = 2'b10;  // Right shift

    # 1
    alu_op = 2'b11;  // And

    # 1
    alu_operar = 0;

    # 1
    alu_op = 2'b00; // No deberia hacer nada

    # 1
    alu_op = 2'b01;  // No deberia hacer nada

    # 1
    alu_op = 2'b10;  // No deberia hacer nada

    # 2
    $finish;
end
endmodule

modules/tb/alu_tb.vcd
$date
	Thu Mar  3 17:27:03 2022
$end
$version
	Icarus Verilog
$end
$timescale
	1ms
$end
$scope module alu_tb $end
$var wire 1 ! alu_z $end
$var wire 16 " alu_out [15:0] $end
$var reg 16 # alu_in_a [15:0] $end
$var reg 16 $ alu_in_b [15:0] $end
$var reg 2 % alu_op [1:0] $end
$var reg 1 & alu_operar $end
$scope module ALU_1 $end
$var wire 16 ' in_a [15:0] $end
$var wire 16 ( in_b [15:0] $end
$var wire 2 ) op [1:0] $end
$var wire 1 & operar $end
$var reg 1 * n $end
$var reg 16 + out [15:0] $end
$var reg 1 , v $end
$var reg 1 ! z $end
$upscope $end
$upscope $end
$enddefinitions $end
#0
$dumpvars
x,
b1111 +
x*
b0 )
b101 (
b1010 '
1&
b0 %
b101 $
b1010 #
b1111 "
0!
$end
#1000
b101 "
b101 +
b1 %
b1 )
#2000
b10 %
b10 )
#3000
1!
b0 "
b0 +
b11 %
b11 )
#4000
0!
b1111111111111011 "
b1111111111111011 +
b0 %
b0 )
b1111111111110110 #
b1111111111110110 '
#5000
b1111111111110001 "
b1111111111110001 +
b1 %
b1 )
#6000
b1111111111111011 "
b1111111111111011 +
b10 %
b10 )
#7000
b100 "
b100 +
b11 %
b11 )
#8000
b101 "
b101 +
0&
#9000
b0 %
b0 )
#10000
b1 %
b1 )
#11000
b10 %
b10 )
